convert2/__init__.py
convert2/__init__.pyc
convert2/parse_date.py
convert2/parse_date.pyc
convert2/parse_datetime.py
convert2/parse_datetime.pyc
convert2/parse_float.py
convert2/parse_float.pyc
convert2/parse_int.py
convert2/parse_int.pyc
convert2/parse_str.py
convert2/parse_str.pyc
convert2/util.py
convert2/util.pyc
convert2/__pycache__/__init__.cpython-34.pyc
convert2/__pycache__/__init__.cpython-35.pyc
convert2/__pycache__/__init__.cpython-36.pyc
convert2/__pycache__/parse_date.cpython-34.pyc
convert2/__pycache__/parse_date.cpython-35.pyc
convert2/__pycache__/parse_date.cpython-36.pyc
convert2/__pycache__/parse_datetime.cpython-34.pyc
convert2/__pycache__/parse_datetime.cpython-35.pyc
convert2/__pycache__/parse_datetime.cpython-36.pyc
convert2/__pycache__/parse_float.cpython-34.pyc
convert2/__pycache__/parse_float.cpython-35.pyc
convert2/__pycache__/parse_float.cpython-36.pyc
convert2/__pycache__/parse_int.cpython-34.pyc
convert2/__pycache__/parse_int.cpython-35.pyc
convert2/__pycache__/parse_int.cpython-36.pyc
convert2/__pycache__/parse_str.cpython-34.pyc
convert2/__pycache__/parse_str.cpython-35.pyc
convert2/__pycache__/parse_str.cpython-36.pyc
convert2/__pycache__/util.cpython-34.pyc
convert2/__pycache__/util.cpython-35.pyc
convert2/__pycache__/util.cpython-36.pyc
convert2/pkg/__init__.py
convert2/pkg/__init__.pyc
convert2/pkg/six.py
convert2/pkg/six.pyc
convert2/pkg/__pycache__/__init__.cpython-34.pyc
convert2/pkg/__pycache__/__init__.cpython-35.pyc
convert2/pkg/__pycache__/__init__.cpython-36.pyc
convert2/pkg/__pycache__/six.cpython-34.pyc
convert2/pkg/__pycache__/six.cpython-35.pyc
convert2/pkg/__pycache__/six.cpython-36.pyc
convert2/pkg/chardet/__init__.py
convert2/pkg/chardet/__init__.pyc
convert2/pkg/chardet/big5freq.py
convert2/pkg/chardet/big5freq.pyc
convert2/pkg/chardet/big5prober.py
convert2/pkg/chardet/big5prober.pyc
convert2/pkg/chardet/chardetect.py
convert2/pkg/chardet/chardistribution.py
convert2-0.0.3.dist-info/DESCRIPTION.rst
convert2-0.0.3.dist-info/METADATA
convert2-0.0.3.dist-info/RECORD
convert2-0.0.3.dist-info/WHEEL
convert2-0.0.3.dist-info/metadata.json
convert2-0.0.3.dist-info/top_level.txt
